README.md
setup.py
baraldi_fib_py/__init__.py
baraldi_fib_py/version.py
baraldi_fib_py.egg-info/PKG-INFO
baraldi_fib_py.egg-info/SOURCES.txt
baraldi_fib_py.egg-info/dependency_links.txt
baraldi_fib_py.egg-info/entry_points.txt
baraldi_fib_py.egg-info/top_level.txt
baraldi_fib_py/cmd/__init__.py
baraldi_fib_py/cmd/fib_num.py
baraldi_fib_py/fib_calcs/__init__.py
baraldi_fib_py/fib_calcs/fib_number.py
baraldi_fib_py/fib_calcs/fib_numbers.py
tests/baraldi_fib_py/__init__.py
tests/baraldi_fib_py/fib_calcs/__init__.py
tests/baraldi_fib_py/fib_calcs/test_fib_number.py
tests/baraldi_fib_py/fib_calcs/test_fib_numbers.py