Metadata-Version: 2.1
Name: baraldi-fib-py
Version: 0.0.3
Summary: Calculates a Fibonacci number
Home-page: https://github.com/Enzo1603/baraldi-fib-py.git
Author: Enzo Baraldi
License: UNKNOWN
Platform: UNKNOWN
Classifier: Development Status :: 4 - Beta
Classifier: Programming Language :: Python :: 3
Classifier: Operating System :: OS Independent
Requires-Python: >=3
